server.py
mseep_nijivoice_mcp_beta-0.1.1.dist-info/licenses/LICENSE
mseep_nijivoice_mcp_beta-0.1.1.dist-info/METADATA
mseep_nijivoice_mcp_beta-0.1.1.dist-info/WHEEL
mseep_nijivoice_mcp_beta-0.1.1.dist-info/entry_points.txt
mseep_nijivoice_mcp_beta-0.1.1.dist-info/top_level.txt
mseep_nijivoice_mcp_beta-0.1.1.dist-info/RECORD
