Metadata-Version: 2.4
Name: mseep-nijivoice-mcp-beta
Version: 0.1.1
Summary: Add your description here
Author-email: mseep <support@skydeck.ai>
Requires-Python: >=3.12
License-File: LICENSE
Requires-Dist: fastmcp>=2.2.8
Requires-Dist: httpx>=0.28.1
Requires-Dist: logger>=1.4
Requires-Dist: pytest>=8.3.5
Requires-Dist: pytest-asyncio>=0.26.0
Requires-Dist: pytest-cov>=4.1.0
Requires-Dist: python-dotenv>=1.1.0
Dynamic: license-file
